Metadata-Version: 2.1
Name: pic-diff-recognizer
Version: 1.0.0
Summary: Selenium plugin library based on image difference recognition and page intelligent exploration
Home-page: https://github.com/amazingTest/Pic-Diff-Recognizer
Author: Yuyi Shao
Author-email: 523314409@qq.com
License: UNKNOWN
Platform: UNKNOWN
Classifier: Programming Language :: Python :: 3
Classifier: License :: OSI Approved :: GNU Affero General Public License v3 or later (AGPLv3+)
Classifier: Operating System :: OS Independent
